pytorch_nn_tools/__init__.py
pytorch_nn_tools/version.py
pytorch_nn_tools/convert/__init__.py
pytorch_nn_tools/devices/__init__.py
pytorch_nn_tools/hook/__init__.py
pytorch_nn_tools/hook/hook.py
pytorch_nn_tools/memory/__init__.py
pytorch_nn_tools/memory/memory.py
pytorch_nn_tools/metrics/__init__.py
pytorch_nn_tools/metrics/accuracy.py
pytorch_nn_tools/structure/__init__.py
pytorch_nn_tools/structure/structure.py
pytorch_nn_tools/train/__init__.py
pytorch_nn_tools/train/checkpoint.py
pytorch_nn_tools/train/progress.py
pytorch_nn_tools/train/metrics/__init__.py
pytorch_nn_tools/train/metrics/history_condition.py
pytorch_nn_tools/train/metrics/processor.py
pytorch_nn_tools/visual/__init__.py
pytorch_nn_tools-0.3.7.dist-info/LICENSE
pytorch_nn_tools-0.3.7.dist-info/METADATA
pytorch_nn_tools-0.3.7.dist-info/WHEEL
pytorch_nn_tools-0.3.7.dist-info/entry_points.txt
pytorch_nn_tools-0.3.7.dist-info/top_level.txt
pytorch_nn_tools-0.3.7.dist-info/RECORD
