Metadata-Version: 2.1
Name: pytorch_nn_tools
Version: 0.3.7
Summary: Tools for NN creation with Pytorch
Home-page: https://github.com/serge-m/pytorch_nn_tools
Author: SergeM
Author-email: serge-m@users.noreply.github.com
License: MIT license
Keywords: pytorch_nn_tools
Platform: UNKNOWN
Classifier: Development Status :: 2 - Pre-Alpha
Classifier: Intended Audience :: Developers
Classifier: License :: OSI Approved :: MIT License
Classifier: Natural Language :: English
Classifier: Programming Language :: Python :: 3
Classifier: Programming Language :: Python :: 3.6
Classifier: Programming Language :: Python :: 3.7
Classifier: Programming Language :: Python :: 3.8
Requires-Python: >=3.6
